README.md
setup.cfg
setup.py
icefun_prog.egg-info/PKG-INFO
icefun_prog.egg-info/SOURCES.txt
icefun_prog.egg-info/dependency_links.txt
icefun_prog.egg-info/entry_points.txt
icefun_prog.egg-info/requires.txt
icefun_prog.egg-info/top_level.txt
icefunprog/__init__.py
icefunprog/icefunprog.py